awlify/__init__.py
awlify/__main__.py
awlify/check_sentence.py
awlify/utils/__init__.py
awlify/utils/awl_full_results.py
awlify/utils/check_word.py
awlify-1.1.2.dist-info/LICENSE
awlify-1.1.2.dist-info/METADATA
awlify-1.1.2.dist-info/WHEEL
awlify-1.1.2.dist-info/top_level.txt
awlify-1.1.2.dist-info/RECORD
