Metadata-Version: 2.1
Name: awlify
Version: 1.1.2
Summary: a simple utility to take in a sentence and output information about the AWL words in it
Home-page: https://github.com/lpmi-13/awlify-python
Author: Adam Leskis
Author-email: leskis@gmail.com
License: MIT
Platform: UNKNOWN
Classifier: License :: OSI Approved :: MIT License
Classifier: Programming Language :: Python :: 3
Classifier: Programming Language :: Python :: 3.6
Requires-Dist: spacy (>=2.0.16)
